{
  "lastUpdated": "2025-01-03T12:16:00.000+0000",
  "twitterEnabled": false,
  "incidents": [
    {
      "loc": [
        50.94879,
        -3.122772
      ],
      "id": "INCD-44813-l",
      "region": "South West"
    },
    {
      "loc": [
        50.73764,
        -3.999995
      ],
      "id": "INCD-44839-l",
      "region": "South West"
    },
    {
      "loc": [
        50.11103,
        -5.268874
      ],
      "id": "INCD-44858-l",
      "region": "South West"
    },
    {
      "loc": [
        51.48253,
        -2.447683
      ],
      "id": "INCD-44855-l",
      "region": "South West"
    },
    {
      "loc": [
        50.71807,
        -3.559252
      ],
      "id": "INCD-44825-l",
      "region": "South West"
    },
    {
      "loc": [
        50.28817,
        -4.805223
      ],
      "id": "INCD-44843-l",
      "region": "South West"
    },
    {
      "loc": [
        51.66989,
        -4.01129
      ],
      "id": "INCD-29290-f",
      "region": "South Wales"
    },
    {
      "loc": [
        51.83295,
        -3.021969
      ],
      "id": "INCD-29173-f",
      "region": "South Wales"
    },
    {
      "loc": [
        51.90468,
        -2.070115
      ],
      "id": "INCD-355856-f",
      "region": "West Midlands"
    },
    {
      "loc": [
        51.9857,
        -2.163115
      ],
      "id": "INCD-32865-m",
      "region": "West Midlands"
    },
    {
      "loc": [
        52.5976,
        -1.980071
      ],
      "id": "INCD-32875-m",
      "region": "West Midlands"
    },
    {
      "loc": [
        51.79559,
        -2.592084
      ],
      "id": "INCD-31942-m",
      "region": "West Midlands"
    },
    {
      "loc": [
        52.68261,
        -1.30968
      ],
      "id": "INCD-71335-h",
      "region": "East Midlands"
    },
    {
      "loc": [
        52.64843,
        -1.368394
      ],
      "id": "INCD-71326-h",
      "region": "East Midlands"
    },
    {
      "loc": [
        52.28296,
        -1.528779
      ],
      "id": "INCD-71295-h",
      "region": "East Midlands"
    },
    {
      "loc": [
        53.21422,
        -1.673109
      ],
      "id": "INCD-71307-h",
      "region": "East Midlands"
    },
    {
      "loc": [
        52.90507,
        -1.882205
      ],
      "id": "INCD-71312-h",
      "region": "East Midlands"
    },
    {
      "loc": [
        52.91866,
        -1.130908
      ],
      "id": "INCD-71338-h",
      "region": "East Midlands"
    },
    {
      "loc": [
        53.08859,
        -0.215076
      ],
      "id": "INCD-71341-h",
      "region": "East Midlands"
    },
    {
      "loc": [
        52.9222,
        -1.411628
      ],
      "id": "INCD-71339-h",
      "region": "East Midlands"
    }
  ],
  "updatePeriod": 30000,
  "incidentStatus": 200,
  "alertSummary": [
    {
      "displayDate": 1724921581191,
      "id": 5,
      "flagAsNew": false
    }
  ]
}
