{
  "lastUpdated": "2026-02-04T11:34:00.000+0000",
  "twitterEnabled": false,
  "incidents": [
    {
      "loc": [
        51.1472,
        -3.057685
      ],
      "id": "INCD-20627-t",
      "region": "South West"
    },
    {
      "loc": [
        51.12333,
        -4.078292
      ],
      "id": "INCD-20616-t",
      "region": "South West"
    },
    {
      "loc": [
        51.44175,
        -2.630026
      ],
      "id": "INCD-84664-l",
      "region": "South West"
    },
    {
      "loc": [
        51.03518,
        -3.309041
      ],
      "id": "INCD-84690-l",
      "region": "South West"
    },
    {
      "loc": [
        50.26201,
        -3.662766
      ],
      "id": "INCD-84678-l",
      "region": "South West"
    },
    {
      "loc": [
        50.1365,
        -5.359646
      ],
      "id": "INCD-84670-l",
      "region": "South West"
    },
    {
      "loc": [
        50.79919,
        -3.453577
      ],
      "id": "INCD-84675-l",
      "region": "South West"
    },
    {
      "loc": [
        51.15108,
        -4.177518
      ],
      "id": "INCD-84580-l",
      "region": "South West"
    },
    {
      "loc": [
        51.03106,
        -3.078312
      ],
      "id": "INCD-84660-l",
      "region": "South West"
    },
    {
      "loc": [
        51.1923,
        -2.545506
      ],
      "id": "INCD-84669-l",
      "region": "South West"
    },
    {
      "loc": [
        51.44639,
        -3.195936
      ],
      "id": "INCD-27166-e",
      "region": "South Wales"
    },
    {
      "loc": [
        51.779,
        -3.999423
      ],
      "id": "INCD-49479-f",
      "region": "South Wales"
    },
    {
      "loc": [
        51.99413,
        -2.43522
      ],
      "id": "INCD-57348-m",
      "region": "West Midlands"
    },
    {
      "loc": [
        52.53353,
        -1.87893
      ],
      "id": "INCD-57347-m",
      "region": "West Midlands"
    },
    {
      "loc": [
        52.50939,
        -1.98886
      ],
      "id": "INCD-57334-m",
      "region": "West Midlands"
    },
    {
      "loc": [
        52.53651,
        -1.807281
      ],
      "id": "INCD-61354-p",
      "region": "West Midlands"
    },
    {
      "loc": [
        52.86969,
        -1.679714
      ],
      "id": "INCD-116044-h",
      "region": "East Midlands"
    },
    {
      "loc": [
        52.64602,
        -1.706726
      ],
      "id": "INCD-116069-h",
      "region": "East Midlands"
    }
  ],
  "updatePeriod": 30000,
  "incidentStatus": 200,
  "alertSummary": [
    {
      "displayDate": 1759671990139,
      "id": 5,
      "flagAsNew": false
    }
  ]
}
