{
  "lastUpdated": "2024-07-18T00:41:00.000+0100",
  "twitterEnabled": 0,
  "incidents": [
    {
      "loc": [
        51.5047,
        -2.696751
      ],
      "id": "INCD-26780-l",
      "region": "South West"
    },
    {
      "loc": [
        51.14794,
        -3.125669
      ],
      "id": "INCD-26846-l",
      "region": "South West"
    },
    {
      "loc": [
        52.21709,
        -1.88372
      ],
      "id": "INCD-22111-m",
      "region": "West Midlands"
    },
    {
      "loc": [
        52.4291,
        -1.857899
      ],
      "id": "INCD-22109-m",
      "region": "West Midlands"
    },
    {
      "loc": [
        52.10375,
        -2.308932
      ],
      "id": "INCD-26179-p",
      "region": "West Midlands"
    },
    {
      "loc": [
        52.27743,
        -2.168744
      ],
      "id": "INCD-26180-p",
      "region": "West Midlands"
    },
    {
      "loc": [
        52.41705,
        -1.525646
      ],
      "id": "INCD-51488-h",
      "region": "East Midlands"
    },
    {
      "loc": [
        52.54575,
        -1.370443
      ],
      "id": "INCD-51420-h",
      "region": "East Midlands"
    },
    {
      "loc": [
        52.77056,
        -0.785009
      ],
      "id": "INCD-51509-h",
      "region": "East Midlands"
    }
  ],
  "updatePeriod": 60000,
  "incidentStatus": 200,
  "alertSummary": [
    {
      "id": 6,
      "published": "Mar 15, 2021, 8:00:00 AM",
      "flagAsNew": false,
      "isDefault": true
    }
  ]
}
