{
  "lastUpdated": "2024-09-26T15:02:00.000+0100",
  "twitterEnabled": false,
  "incidents": [
    {
      "loc": [
        51.19948,
        -4.111221
      ],
      "id": "INCD-32344-l",
      "region": "South West"
    },
    {
      "loc": [
        50.41184,
        -4.102432
      ],
      "id": "INCD-32301-l",
      "region": "South West"
    },
    {
      "loc": [
        50.7901,
        -3.205779
      ],
      "id": "INCD-11302-t",
      "region": "South West"
    },
    {
      "loc": [
        50.85932,
        -3.396466
      ],
      "id": "INCD-32308-l",
      "region": "South West"
    },
    {
      "loc": [
        51.1322,
        -2.985968
      ],
      "id": "INCD-11317-t",
      "region": "South West"
    },
    {
      "loc": [
        51.19968,
        -3.471087
      ],
      "id": "INCD-32297-l",
      "region": "South West"
    },
    {
      "loc": [
        50.54681,
        -3.515951
      ],
      "id": "INCD-32205-l",
      "region": "South West"
    },
    {
      "loc": [
        50.3474,
        -3.682207
      ],
      "id": "INCD-32329-l",
      "region": "South West"
    },
    {
      "loc": [
        51.4347,
        -2.846796
      ],
      "id": "INCD-7222-u",
      "region": "South West"
    },
    {
      "loc": [
        50.24,
        -3.683597
      ],
      "id": "INCD-32307-l",
      "region": "South West"
    },
    {
      "loc": [
        51.69984,
        -2.207894
      ],
      "id": "INCD-30166-p",
      "region": "West Midlands"
    },
    {
      "loc": [
        51.88446,
        -2.111461
      ],
      "id": "INCD-26507-m",
      "region": "West Midlands"
    },
    {
      "loc": [
        51.72436,
        -2.523933
      ],
      "id": "INCD-26440-m",
      "region": "West Midlands"
    },
    {
      "loc": [
        52.04428,
        -1.339513
      ],
      "id": "INCD-26515-m",
      "region": "West Midlands"
    },
    {
      "loc": [
        52.07035,
        -1.3494
      ],
      "id": "INCD-26516-m",
      "region": "West Midlands"
    },
    {
      "loc": [
        52.36963,
        -1.76744
      ],
      "id": "INCD-8605-l",
      "region": "West Midlands"
    },
    {
      "loc": [
        51.725,
        -2.376953
      ],
      "id": "INCD-26514-m",
      "region": "West Midlands"
    },
    {
      "loc": [
        53.09659,
        -1.224922
      ],
      "id": "INCD-59715-h",
      "region": "East Midlands"
    },
    {
      "loc": [
        52.9105,
        -1.364277
      ],
      "id": "INCD-59717-h",
      "region": "East Midlands"
    },
    {
      "loc": [
        52.53901,
        -1.43922
      ],
      "id": "INCD-59651-h",
      "region": "East Midlands"
    },
    {
      "loc": [
        52.89502,
        -1.157097
      ],
      "id": "INCD-59712-h",
      "region": "East Midlands"
    },
    {
      "loc": [
        52.38547,
        -1.271431
      ],
      "id": "INCD-59713-h",
      "region": "East Midlands"
    },
    {
      "loc": [
        52.48706,
        -0.670922
      ],
      "id": "INCD-59684-h",
      "region": "East Midlands"
    },
    {
      "loc": [
        52.41715,
        -1.480609
      ],
      "id": "INCD-59708-h",
      "region": "East Midlands"
    },
    {
      "loc": [
        52.92123,
        -0.623202
      ],
      "id": "INCD-59635-h",
      "region": "East Midlands"
    },
    {
      "loc": [
        53.17801,
        -1.095527
      ],
      "id": "INCD-59704-h",
      "region": "East Midlands"
    },
    {
      "loc": [
        52.99452,
        -0.414196
      ],
      "id": "INCD-59628-h",
      "region": "East Midlands"
    }
  ],
  "updatePeriod": 30000,
  "incidentStatus": 200,
  "alertSummary": [
    {
      "displayDate": 1727097345943,
      "id": 6,
      "flagAsNew": true
    }
  ]
}
