{
  "lastUpdated": "2025-04-16T11:42:00.000+0100",
  "twitterEnabled": false,
  "incidents": [
    {
      "loc": [
        51.02363,
        -4.207074
      ],
      "id": "INCD-9165-u",
      "region": "South West"
    },
    {
      "loc": [
        51.1192,
        -2.988763
      ],
      "id": "INCD-54479-l",
      "region": "South West"
    },
    {
      "loc": [
        51.0683,
        -4.148492
      ],
      "id": "INCD-54430-l",
      "region": "South West"
    },
    {
      "loc": [
        50.6306,
        -3.396011
      ],
      "id": "INCD-54376-l",
      "region": "South West"
    },
    {
      "loc": [
        50.34534,
        -4.768039
      ],
      "id": "INCD-54415-l",
      "region": "South West"
    },
    {
      "loc": [
        50.42153,
        -3.590273
      ],
      "id": "INCD-54478-l",
      "region": "South West"
    },
    {
      "loc": [
        51.0949,
        -4.07596
      ],
      "id": "INCD-54461-l",
      "region": "South West"
    },
    {
      "loc": [
        50.7936,
        -3.356068
      ],
      "id": "INCD-54414-l",
      "region": "South West"
    },
    {
      "loc": [
        51.54029,
        -2.566745
      ],
      "id": "INCD-9160-u",
      "region": "South West"
    },
    {
      "loc": [
        51.35963,
        -2.366012
      ],
      "id": "INCD-54157-l",
      "region": "South West"
    },
    {
      "loc": [
        50.4159,
        -4.099051
      ],
      "id": "INCD-54464-l",
      "region": "South West"
    },
    {
      "loc": [
        51.02363,
        -4.207074
      ],
      "id": "INCD-9164-u",
      "region": "South West"
    },
    {
      "loc": [
        51.15065,
        -2.869621
      ],
      "id": "INCD-54421-l",
      "region": "South West"
    },
    {
      "loc": [
        50.24297,
        -5.220021
      ],
      "id": "INCD-54440-l",
      "region": "South West"
    },
    {
      "loc": [
        50.12525,
        -5.67701
      ],
      "id": "INCD-54448-l",
      "region": "South West"
    },
    {
      "loc": [
        50.39115,
        -4.172848
      ],
      "id": "INCD-54471-l",
      "region": "South West"
    },
    {
      "loc": [
        50.41873,
        -4.12688
      ],
      "id": "INCD-37300-v",
      "region": "South West"
    },
    {
      "loc": [
        50.52209,
        -3.580757
      ],
      "id": "INCD-54337-l",
      "region": "South West"
    },
    {
      "loc": [
        51.33235,
        -2.810817
      ],
      "id": "INCD-54458-l",
      "region": "South West"
    },
    {
      "loc": [
        51.99657,
        -2.089295
      ],
      "id": "INCD-43054-p",
      "region": "West Midlands"
    },
    {
      "loc": [
        52.5181,
        -2.112575
      ],
      "id": "INCD-43060-p",
      "region": "West Midlands"
    },
    {
      "loc": [
        51.68834,
        -2.392108
      ],
      "id": "INCD-43053-p",
      "region": "West Midlands"
    },
    {
      "loc": [
        51.43384,
        -2.492995
      ],
      "id": "INCD-43046-p",
      "region": "West Midlands"
    },
    {
      "loc": [
        52.40392,
        -2.887991
      ],
      "id": "INCD-38193-m",
      "region": "West Midlands"
    },
    {
      "loc": [
        52.88386,
        -2.138756
      ],
      "id": "INCD-38215-m",
      "region": "West Midlands"
    },
    {
      "loc": [
        52.49433,
        -1.843064
      ],
      "id": "INCD-38187-m",
      "region": "West Midlands"
    },
    {
      "loc": [
        51.44306,
        -2.524735
      ],
      "id": "INCD-43065-p",
      "region": "West Midlands"
    },
    {
      "loc": [
        51.74011,
        -2.238347
      ],
      "id": "INCD-38222-m",
      "region": "West Midlands"
    },
    {
      "loc": [
        52.10233,
        -1.781956
      ],
      "id": "INCD-38209-m",
      "region": "West Midlands"
    },
    {
      "loc": [
        51.73348,
        -2.23954
      ],
      "id": "INCD-43049-p",
      "region": "West Midlands"
    },
    {
      "loc": [
        53.34051,
        -0.863992
      ],
      "id": "INCD-83009-h",
      "region": "East Midlands"
    },
    {
      "loc": [
        52.61042,
        -1.090398
      ],
      "id": "INCD-83025-h",
      "region": "East Midlands"
    },
    {
      "loc": [
        52.24133,
        -0.985806
      ],
      "id": "INCD-83028-h",
      "region": "East Midlands"
    },
    {
      "loc": [
        53.12889,
        -1.039361
      ],
      "id": "INCD-82778-h",
      "region": "East Midlands"
    },
    {
      "loc": [
        52.58205,
        -1.63
      ],
      "id": "INCD-83014-h",
      "region": "East Midlands"
    },
    {
      "loc": [
        52.81188,
        -0.676616
      ],
      "id": "INCD-83000-h",
      "region": "East Midlands"
    }
  ],
  "updatePeriod": 30000,
  "incidentStatus": 200,
  "alertSummary": [
    {
      "displayDate": 1724921581191,
      "id": 5,
      "flagAsNew": false
    }
  ]
}
