{
  "lastUpdated": "2025-12-01T13:29:00.000+0000",
  "twitterEnabled": false,
  "incidents": [
    {
      "loc": [
        50.64165,
        -3.387386
      ],
      "id": "INCD-11178-u",
      "region": "South West"
    },
    {
      "loc": [
        51.44043,
        -2.573795
      ],
      "id": "INCD-11180-u",
      "region": "South West"
    },
    {
      "loc": [
        51.4321,
        -2.57924
      ],
      "id": "INCD-11142-u",
      "region": "South West"
    },
    {
      "loc": [
        50.16189,
        -5.1844
      ],
      "id": "INCD-11179-u",
      "region": "South West"
    },
    {
      "loc": [
        51.0742,
        -3.003934
      ],
      "id": "INCD-11197-u",
      "region": "South West"
    },
    {
      "loc": [
        50.51944,
        -3.528319
      ],
      "id": "INCD-18791-t",
      "region": "South West"
    },
    {
      "loc": [
        50.79112,
        -3.206102
      ],
      "id": "INCD-11202-u",
      "region": "South West"
    },
    {
      "loc": [
        50.38255,
        -4.034939
      ],
      "id": "INCD-11190-u",
      "region": "South West"
    },
    {
      "loc": [
        50.34872,
        -3.572602
      ],
      "id": "INCD-11150-u",
      "region": "South West"
    },
    {
      "loc": [
        51.50175,
        -2.50754
      ],
      "id": "INCD-11176-u",
      "region": "South West"
    },
    {
      "loc": [
        50.7131,
        -3.552855
      ],
      "id": "INCD-19365-t",
      "region": "South West"
    },
    {
      "loc": [
        50.04006,
        -5.20683
      ],
      "id": "INCD-11136-u",
      "region": "South West"
    },
    {
      "loc": [
        51.46247,
        -2.495492
      ],
      "id": "INCD-11174-u",
      "region": "South West"
    },
    {
      "loc": [
        51.44122,
        -2.577632
      ],
      "id": "INCD-11177-u",
      "region": "South West"
    },
    {
      "loc": [
        51.79571,
        -3.198428
      ],
      "id": "INCD-5132-j",
      "region": "South Wales"
    },
    {
      "loc": [
        51.97153,
        -3.98967
      ],
      "id": "INCD-5139-j",
      "region": "South Wales"
    },
    {
      "loc": [
        51.7705,
        -3.752824
      ],
      "id": "INCD-5153-j",
      "region": "South Wales"
    },
    {
      "loc": [
        51.85,
        -4.949514
      ],
      "id": "INCD-5136-j",
      "region": "South Wales"
    },
    {
      "loc": [
        51.39584,
        -3.389301
      ],
      "id": "INCD-5189-j",
      "region": "South Wales"
    },
    {
      "loc": [
        51.64158,
        -2.672995
      ],
      "id": "INCD-5161-j",
      "region": "South Wales"
    },
    {
      "loc": [
        51.86465,
        -4.19121
      ],
      "id": "INCD-45938-f",
      "region": "South Wales"
    },
    {
      "loc": [
        52.55577,
        -2.105031
      ],
      "id": "INCD-52781-m",
      "region": "West Midlands"
    },
    {
      "loc": [
        52.56378,
        -1.820334
      ],
      "id": "INCD-57119-p",
      "region": "West Midlands"
    },
    {
      "loc": [
        51.8523,
        -2.239564
      ],
      "id": "INCD-57107-p",
      "region": "West Midlands"
    },
    {
      "loc": [
        52.00458,
        -2.143313
      ],
      "id": "INCD-52796-m",
      "region": "West Midlands"
    },
    {
      "loc": [
        52.51034,
        -1.756238
      ],
      "id": "INCD-57124-p",
      "region": "West Midlands"
    },
    {
      "loc": [
        52.72636,
        -2.433876
      ],
      "id": "INCD-52763-m",
      "region": "West Midlands"
    },
    {
      "loc": [
        52.65019,
        -1.923745
      ],
      "id": "INCD-52766-m",
      "region": "West Midlands"
    },
    {
      "loc": [
        52.53353,
        -1.87893
      ],
      "id": "INCD-57125-p",
      "region": "West Midlands"
    },
    {
      "loc": [
        52.93532,
        -1.078782
      ],
      "id": "INCD-108411-h",
      "region": "East Midlands"
    },
    {
      "loc": [
        53.00447,
        -1.151897
      ],
      "id": "INCD-108427-h",
      "region": "East Midlands"
    },
    {
      "loc": [
        52.5385,
        -1.398516
      ],
      "id": "INCD-108352-h",
      "region": "East Midlands"
    },
    {
      "loc": [
        53.14328,
        -1.25362
      ],
      "id": "INCD-108415-h",
      "region": "East Midlands"
    },
    {
      "loc": [
        52.6131,
        -1.620932
      ],
      "id": "INCD-108433-h",
      "region": "East Midlands"
    },
    {
      "loc": [
        53.22878,
        -1.20173
      ],
      "id": "INCD-108400-h",
      "region": "East Midlands"
    },
    {
      "loc": [
        52.70251,
        -1.60426
      ],
      "id": "INCD-108423-h",
      "region": "East Midlands"
    },
    {
      "loc": [
        52.46094,
        -1.532358
      ],
      "id": "INCD-108361-h",
      "region": "East Midlands"
    },
    {
      "loc": [
        52.90516,
        -1.227688
      ],
      "id": "INCD-108402-h",
      "region": "East Midlands"
    },
    {
      "loc": [
        53.28102,
        -1.364238
      ],
      "id": "INCD-106576-h",
      "region": "East Midlands"
    },
    {
      "loc": [
        52.37422,
        -1.509551
      ],
      "id": "INCD-108417-h",
      "region": "East Midlands"
    }
  ],
  "updatePeriod": 30000,
  "incidentStatus": 200,
  "alertSummary": [
    {
      "displayDate": 1759671990139,
      "id": 5,
      "flagAsNew": false
    }
  ]
}
