{
  "lastUpdated": "2025-06-30T20:00:00.000+0100",
  "twitterEnabled": false,
  "incidents": [
    {
      "loc": [
        50.73158,
        -2.933648
      ],
      "id": "INCD-61263-l",
      "region": "South West"
    },
    {
      "loc": [
        50.43545,
        -4.098324
      ],
      "id": "INCD-61256-l",
      "region": "South West"
    },
    {
      "loc": [
        50.12313,
        -5.436594
      ],
      "id": "INCD-61231-l",
      "region": "South West"
    },
    {
      "loc": [
        51.58694,
        -4.04765
      ],
      "id": "INCD-37600-f",
      "region": "South Wales"
    },
    {
      "loc": [
        51.61755,
        -3.005668
      ],
      "id": "INCD-4429-j",
      "region": "South Wales"
    },
    {
      "loc": [
        52.50073,
        -1.764996
      ],
      "id": "INCD-47098-p",
      "region": "West Midlands"
    },
    {
      "loc": [
        52.39067,
        -2.05237
      ],
      "id": "INCD-47114-p",
      "region": "West Midlands"
    },
    {
      "loc": [
        51.94618,
        -1.76671
      ],
      "id": "INCD-47108-p",
      "region": "West Midlands"
    },
    {
      "loc": [
        51.5898,
        -2.53908
      ],
      "id": "INCD-47090-p",
      "region": "West Midlands"
    },
    {
      "loc": [
        52.37724,
        -1.779299
      ],
      "id": "INCD-47097-p",
      "region": "West Midlands"
    },
    {
      "loc": [
        52.28784,
        -1.948029
      ],
      "id": "INCD-42437-m",
      "region": "West Midlands"
    },
    {
      "loc": [
        52.0561,
        -2.706409
      ],
      "id": "INCD-47111-p",
      "region": "West Midlands"
    },
    {
      "loc": [
        53.2164,
        -1.689326
      ],
      "id": "INCD-90938-h",
      "region": "East Midlands"
    },
    {
      "loc": [
        52.97531,
        -0.023518
      ],
      "id": "INCD-90828-h",
      "region": "East Midlands"
    },
    {
      "loc": [
        52.94999,
        -1.85069
      ],
      "id": "INCD-90900-h",
      "region": "East Midlands"
    },
    {
      "loc": [
        52.3486,
        -1.56726
      ],
      "id": "INCD-90118-h",
      "region": "East Midlands"
    },
    {
      "loc": [
        52.82556,
        -1.652642
      ],
      "id": "INCD-90824-h",
      "region": "East Midlands"
    },
    {
      "loc": [
        52.92139,
        -0.057304
      ],
      "id": "INCD-90933-h",
      "region": "East Midlands"
    },
    {
      "loc": [
        52.93532,
        -1.078782
      ],
      "id": "INCD-90910-h",
      "region": "East Midlands"
    },
    {
      "loc": [
        53.08252,
        -1.571798
      ],
      "id": "INCD-90887-h",
      "region": "East Midlands"
    },
    {
      "loc": [
        52.92361,
        -1.03085
      ],
      "id": "INCD-90939-h",
      "region": "East Midlands"
    },
    {
      "loc": [
        52.595,
        -0.71901
      ],
      "id": "INCD-90890-h",
      "region": "East Midlands"
    },
    {
      "loc": [
        52.53717,
        -1.023442
      ],
      "id": "INCD-90896-h",
      "region": "East Midlands"
    },
    {
      "loc": [
        52.56914,
        -1.4126
      ],
      "id": "INCD-90940-h",
      "region": "East Midlands"
    }
  ],
  "updatePeriod": 30000,
  "incidentStatus": 200,
  "alertSummary": [
    {
      "displayDate": 1724921581191,
      "id": 5,
      "flagAsNew": false
    }
  ]
}
