{
  "lastUpdated": "2025-01-15T07:31:00.000+0000",
  "twitterEnabled": false,
  "incidents": [
    {
      "loc": [
        50.67371,
        -3.840204
      ],
      "id": "INCD-46064-l",
      "region": "South West"
    },
    {
      "loc": [
        52.60533,
        -1.915466
      ],
      "id": "INCD-37733-p",
      "region": "West Midlands"
    },
    {
      "loc": [
        52.5487,
        -2.054181
      ],
      "id": "INCD-37745-p",
      "region": "West Midlands"
    },
    {
      "loc": [
        52.38041,
        -2.226975
      ],
      "id": "INCD-37742-p",
      "region": "West Midlands"
    },
    {
      "loc": [
        52.50849,
        -1.449845
      ],
      "id": "INCD-72973-h",
      "region": "East Midlands"
    },
    {
      "loc": [
        52.64856,
        -0.475759
      ],
      "id": "INCD-72981-h",
      "region": "East Midlands"
    },
    {
      "loc": [
        52.74863,
        -1.364398
      ],
      "id": "INCD-72953-h",
      "region": "East Midlands"
    }
  ],
  "updatePeriod": 30000,
  "incidentStatus": 200,
  "alertSummary": [
    {
      "displayDate": 1724921581191,
      "id": 5,
      "flagAsNew": false
    }
  ]
}
