{
  "lastUpdated": "2026-05-15T23:36:00.000+0100",
  "twitterEnabled": false,
  "incidents": [
    {
      "loc": [
        50.73444,
        -3.502729
      ],
      "id": "INCD-91768-l",
      "region": "South West"
    },
    {
      "loc": [
        51.70357,
        -3.039195
      ],
      "id": "INCD-53755-f",
      "region": "South Wales"
    },
    {
      "loc": [
        52.48144,
        -1.744367
      ],
      "id": "INCD-63904-m",
      "region": "West Midlands"
    },
    {
      "loc": [
        52.5471,
        -1.88601
      ],
      "id": "INCD-66446-p",
      "region": "West Midlands"
    },
    {
      "loc": [
        52.58054,
        -1.875652
      ],
      "id": "INCD-66452-p",
      "region": "West Midlands"
    },
    {
      "loc": [
        52.50754,
        -2.071854
      ],
      "id": "INCD-63837-m",
      "region": "West Midlands"
    },
    {
      "loc": [
        52.95234,
        -1.14793
      ],
      "id": "INCD-126031-h",
      "region": "East Midlands"
    },
    {
      "loc": [
        52.98067,
        -0.303331
      ],
      "id": "INCD-7510-n",
      "region": "East Midlands"
    },
    {
      "loc": [
        52.2867,
        -1.767141
      ],
      "id": "INCD-126040-h",
      "region": "East Midlands"
    }
  ],
  "updatePeriod": 30000,
  "incidentStatus": 200,
  "alertSummary": [
    {
      "displayDate": 1759671990139,
      "id": 5,
      "flagAsNew": false
    }
  ]
}
