{
  "lastUpdated": "2025-08-18T16:42:00.000+0100",
  "twitterEnabled": false,
  "incidents": [
    {
      "loc": [
        51.36338,
        -2.92672
      ],
      "id": "INCD-65951-l",
      "region": "South West"
    },
    {
      "loc": [
        50.21067,
        -5.117839
      ],
      "id": "INCD-66019-l",
      "region": "South West"
    },
    {
      "loc": [
        50.7239,
        -3.531873
      ],
      "id": "INCD-66027-l",
      "region": "South West"
    },
    {
      "loc": [
        51.02743,
        -3.8293
      ],
      "id": "INCD-65977-l",
      "region": "South West"
    },
    {
      "loc": [
        51.32261,
        -2.98056
      ],
      "id": "INCD-66018-l",
      "region": "South West"
    },
    {
      "loc": [
        51.09541,
        -4.137082
      ],
      "id": "INCD-66023-l",
      "region": "South West"
    },
    {
      "loc": [
        51.06626,
        -4.039638
      ],
      "id": "INCD-65965-l",
      "region": "South West"
    },
    {
      "loc": [
        51.12784,
        -3.00924
      ],
      "id": "INCD-65980-l",
      "region": "South West"
    },
    {
      "loc": [
        51.1416,
        -2.981851
      ],
      "id": "INCD-66002-l",
      "region": "South West"
    },
    {
      "loc": [
        50.42206,
        -4.26117
      ],
      "id": "INCD-66035-l",
      "region": "South West"
    },
    {
      "loc": [
        51.61415,
        -3.941828
      ],
      "id": "INCD-39997-f",
      "region": "South Wales"
    },
    {
      "loc": [
        51.69968,
        -4.129278
      ],
      "id": "INCD-39995-f",
      "region": "South Wales"
    },
    {
      "loc": [
        51.69273,
        -2.941376
      ],
      "id": "INCD-39990-f",
      "region": "South Wales"
    },
    {
      "loc": [
        51.59532,
        -3.349788
      ],
      "id": "INCD-39968-f",
      "region": "South Wales"
    },
    {
      "loc": [
        51.69658,
        -3.2235
      ],
      "id": "INCD-39988-f",
      "region": "South Wales"
    },
    {
      "loc": [
        52.40412,
        -1.748253
      ],
      "id": "INCD-50152-p",
      "region": "West Midlands"
    },
    {
      "loc": [
        52.01391,
        -1.31994
      ],
      "id": "INCD-50136-p",
      "region": "West Midlands"
    },
    {
      "loc": [
        53.00811,
        -2.342494
      ],
      "id": "INCD-45526-m",
      "region": "West Midlands"
    },
    {
      "loc": [
        52.69398,
        -2.436337
      ],
      "id": "INCD-45512-m",
      "region": "West Midlands"
    },
    {
      "loc": [
        52.47672,
        -1.791434
      ],
      "id": "INCD-50154-p",
      "region": "West Midlands"
    },
    {
      "loc": [
        53.29303,
        -1.445208
      ],
      "id": "INCD-96499-h",
      "region": "East Midlands"
    },
    {
      "loc": [
        52.44904,
        -1.250622
      ],
      "id": "INCD-96545-h",
      "region": "East Midlands"
    },
    {
      "loc": [
        52.38637,
        -0.581258
      ],
      "id": "INCD-96563-h",
      "region": "East Midlands"
    },
    {
      "loc": [
        52.26918,
        -0.915458
      ],
      "id": "INCD-96582-h",
      "region": "East Midlands"
    },
    {
      "loc": [
        53.10337,
        0.024908
      ],
      "id": "INCD-96571-h",
      "region": "East Midlands"
    },
    {
      "loc": [
        52.76715,
        -0.383769
      ],
      "id": "INCD-96530-h",
      "region": "East Midlands"
    }
  ],
  "updatePeriod": 30000,
  "incidentStatus": 200,
  "alertSummary": [
    {
      "displayDate": 1724921581191,
      "id": 5,
      "flagAsNew": false
    }
  ]
}
