{
  "lastUpdated": "2024-12-30T12:36:00.000+0000",
  "twitterEnabled": false,
  "incidents": [
    {
      "loc": [
        51.11907,
        -2.988989
      ],
      "id": "INCD-44417-l",
      "region": "South West"
    },
    {
      "loc": [
        50.48169,
        -3.567879
      ],
      "id": "INCD-44005-l",
      "region": "South West"
    },
    {
      "loc": [
        50.54419,
        -4.904587
      ],
      "id": "INCD-35635-v",
      "region": "South West"
    },
    {
      "loc": [
        52.50754,
        -1.965716
      ],
      "id": "INCD-36674-p",
      "region": "West Midlands"
    },
    {
      "loc": [
        52.58979,
        -2.259025
      ],
      "id": "INCD-32647-m",
      "region": "West Midlands"
    },
    {
      "loc": [
        52.70205,
        -2.559706
      ],
      "id": "INCD-32642-m",
      "region": "West Midlands"
    },
    {
      "loc": [
        51.79559,
        -2.592084
      ],
      "id": "INCD-31942-m",
      "region": "West Midlands"
    },
    {
      "loc": [
        52.5469,
        -2.143337
      ],
      "id": "INCD-32623-m",
      "region": "West Midlands"
    },
    {
      "loc": [
        53.1075,
        -0.525641
      ],
      "id": "INCD-70908-h",
      "region": "East Midlands"
    },
    {
      "loc": [
        53.1396,
        -1.47915
      ],
      "id": "INCD-70890-h",
      "region": "East Midlands"
    }
  ],
  "updatePeriod": 30000,
  "incidentStatus": 200,
  "alertSummary": [
    {
      "displayDate": 1724921581191,
      "id": 5,
      "flagAsNew": false
    }
  ]
}
