{
  "lastUpdated": "2024-06-05T21:24:00.000+0100",
  "twitterEnabled": 0,
  "incidents": [
    {
      "loc": [
        50.36554,
        -5.052814
      ],
      "id": "INCD-23822-l",
      "region": "South West"
    },
    {
      "loc": [
        51.20641,
        -3.4773
      ],
      "id": "INCD-23807-l",
      "region": "South West"
    },
    {
      "loc": [
        50.4175,
        -3.580298
      ],
      "id": "INCD-9588-t",
      "region": "South West"
    },
    {
      "loc": [
        50.98352,
        -2.745204
      ],
      "id": "INCD-23806-l",
      "region": "South West"
    },
    {
      "loc": [
        50.88742,
        -3.376279
      ],
      "id": "INCD-23829-l",
      "region": "South West"
    },
    {
      "loc": [
        51.47052,
        -2.516829
      ],
      "id": "INCD-23793-l",
      "region": "South West"
    },
    {
      "loc": [
        50.62378,
        -3.446704
      ],
      "id": "INCD-9591-t",
      "region": "South West"
    },
    {
      "loc": [
        51.8503,
        -2.515232
      ],
      "id": "INCD-23918-p",
      "region": "West Midlands"
    },
    {
      "loc": [
        51.84917,
        -2.256707
      ],
      "id": "INCD-23914-p",
      "region": "West Midlands"
    },
    {
      "loc": [
        53.04296,
        -2.204297
      ],
      "id": "INCD-17069-m",
      "region": "West Midlands"
    },
    {
      "loc": [
        52.28895,
        -1.7743
      ],
      "id": "INCD-47061-h",
      "region": "East Midlands"
    },
    {
      "loc": [
        52.58955,
        -1.244967
      ],
      "id": "INCD-47007-h",
      "region": "East Midlands"
    },
    {
      "loc": [
        52.90309,
        -1.484528
      ],
      "id": "INCD-47114-h",
      "region": "East Midlands"
    }
  ],
  "updatePeriod": 60000,
  "incidentStatus": 200,
  "alertSummary": [
    {
      "id": 6,
      "published": "Mar 15, 2021, 8:00:00 AM",
      "flagAsNew": false,
      "isDefault": true
    }
  ]
}
