{
  "lastUpdated": "2024-07-04T08:42:00.000+0100",
  "twitterEnabled": 0,
  "incidents": [
    {
      "loc": [
        50.41907,
        -4.150757
      ],
      "id": "INCD-25729-l",
      "region": "South West"
    },
    {
      "loc": [
        50.43306,
        -4.100387
      ],
      "id": "INCD-25732-l",
      "region": "South West"
    },
    {
      "loc": [
        50.41,
        -4.102378
      ],
      "id": "INCD-25739-l",
      "region": "South West"
    },
    {
      "loc": [
        51.59358,
        -3.798452
      ],
      "id": "INCD-16029-f",
      "region": "South Wales"
    },
    {
      "loc": [
        51.90077,
        -2.092883
      ],
      "id": "INCD-25450-p",
      "region": "West Midlands"
    },
    {
      "loc": [
        52.67049,
        -2.421994
      ],
      "id": "INCD-21353-m",
      "region": "West Midlands"
    },
    {
      "loc": [
        53.04296,
        -2.204297
      ],
      "id": "INCD-17069-m",
      "region": "West Midlands"
    },
    {
      "loc": [
        51.8506,
        -2.215253
      ],
      "id": "INCD-21356-m",
      "region": "West Midlands"
    },
    {
      "loc": [
        53.14052,
        -1.040702
      ],
      "id": "INCD-50086-h",
      "region": "East Midlands"
    }
  ],
  "updatePeriod": 60000,
  "incidentStatus": 200,
  "alertSummary": [
    {
      "id": 6,
      "published": "Mar 15, 2021, 8:00:00 AM",
      "flagAsNew": false,
      "isDefault": true
    }
  ]
}
