{
  "lastUpdated": "2024-12-15T13:18:00.000+0000",
  "twitterEnabled": false,
  "incidents": [
    {
      "loc": [
        50.20924,
        -5.38939
      ],
      "id": "INCD-35395-v",
      "region": "South West"
    },
    {
      "loc": [
        51.20896,
        -4.098138
      ],
      "id": "INCD-14085-t",
      "region": "South West"
    },
    {
      "loc": [
        50.15455,
        -5.66918
      ],
      "id": "INCD-35440-v",
      "region": "South West"
    },
    {
      "loc": [
        50.15962,
        -5.13766
      ],
      "id": "INCD-35438-v",
      "region": "South West"
    },
    {
      "loc": [
        50.37527,
        -4.936196
      ],
      "id": "INCD-42371-l",
      "region": "South West"
    },
    {
      "loc": [
        50.1522,
        -5.657307
      ],
      "id": "INCD-35420-v",
      "region": "South West"
    },
    {
      "loc": [
        50.6314,
        -4.356317
      ],
      "id": "INCD-35430-v",
      "region": "South West"
    },
    {
      "loc": [
        51.33838,
        -2.961617
      ],
      "id": "INCD-8054-u",
      "region": "South West"
    },
    {
      "loc": [
        50.26132,
        -5.115702
      ],
      "id": "INCD-35443-v",
      "region": "South West"
    },
    {
      "loc": [
        50.23778,
        -5.193246
      ],
      "id": "INCD-35434-v",
      "region": "South West"
    },
    {
      "loc": [
        51.13027,
        -3.94194
      ],
      "id": "INCD-14051-t",
      "region": "South West"
    },
    {
      "loc": [
        50.0531,
        -5.127825
      ],
      "id": "INCD-8066-u",
      "region": "South West"
    },
    {
      "loc": [
        51.19948,
        -4.111221
      ],
      "id": "INCD-41788-l",
      "region": "South West"
    },
    {
      "loc": [
        50.82651,
        -4.506746
      ],
      "id": "INCD-42402-l",
      "region": "South West"
    },
    {
      "loc": [
        50.0531,
        -5.127825
      ],
      "id": "INCD-8050-u",
      "region": "South West"
    },
    {
      "loc": [
        50.9036,
        -3.705379
      ],
      "id": "INCD-41957-l",
      "region": "South West"
    },
    {
      "loc": [
        50.98063,
        -3.533031
      ],
      "id": "INCD-13990-t",
      "region": "South West"
    },
    {
      "loc": [
        51.39731,
        -2.320776
      ],
      "id": "INCD-42295-l",
      "region": "South West"
    },
    {
      "loc": [
        50.52407,
        -4.989157
      ],
      "id": "INCD-35408-v",
      "region": "South West"
    },
    {
      "loc": [
        50.78786,
        -3.819798
      ],
      "id": "INCD-42414-l",
      "region": "South West"
    },
    {
      "loc": [
        50.34256,
        -5.111137
      ],
      "id": "INCD-8055-u",
      "region": "South West"
    },
    {
      "loc": [
        50.15477,
        -5.65286
      ],
      "id": "INCD-35431-v",
      "region": "South West"
    },
    {
      "loc": [
        50.77722,
        -4.356877
      ],
      "id": "INCD-42301-l",
      "region": "South West"
    },
    {
      "loc": [
        51.19948,
        -4.111221
      ],
      "id": "INCD-8060-u",
      "region": "South West"
    },
    {
      "loc": [
        50.90955,
        -3.662296
      ],
      "id": "INCD-41717-l",
      "region": "South West"
    },
    {
      "loc": [
        50.79061,
        -3.669041
      ],
      "id": "INCD-42348-l",
      "region": "South West"
    },
    {
      "loc": [
        50.34003,
        -5.162052
      ],
      "id": "INCD-35412-v",
      "region": "South West"
    },
    {
      "loc": [
        51.19398,
        -4.014732
      ],
      "id": "INCD-42379-l",
      "region": "South West"
    },
    {
      "loc": [
        50.90271,
        -4.5042
      ],
      "id": "INCD-8059-u",
      "region": "South West"
    },
    {
      "loc": [
        50.25027,
        -5.285206
      ],
      "id": "INCD-35426-v",
      "region": "South West"
    },
    {
      "loc": [
        50.76726,
        -4.543912
      ],
      "id": "INCD-42216-l",
      "region": "South West"
    },
    {
      "loc": [
        50.11377,
        -5.572766
      ],
      "id": "INCD-35423-v",
      "region": "South West"
    },
    {
      "loc": [
        51.79184,
        -4.97677
      ],
      "id": "INCD-27863-f",
      "region": "South Wales"
    },
    {
      "loc": [
        51.8659,
        -3.129434
      ],
      "id": "INCD-24571-f",
      "region": "South Wales"
    },
    {
      "loc": [
        51.47527,
        -3.703118
      ],
      "id": "INCD-27860-f",
      "region": "South Wales"
    },
    {
      "loc": [
        52.03575,
        -4.471922
      ],
      "id": "INCD-24735-f",
      "region": "South Wales"
    },
    {
      "loc": [
        51.47881,
        -3.257596
      ],
      "id": "INCD-27857-f",
      "region": "South Wales"
    },
    {
      "loc": [
        51.83881,
        -3.01386
      ],
      "id": "INCD-24190-f",
      "region": "South Wales"
    },
    {
      "loc": [
        51.68435,
        -4.119705
      ],
      "id": "INCD-27745-f",
      "region": "South Wales"
    },
    {
      "loc": [
        51.89723,
        -3.988403
      ],
      "id": "INCD-27606-f",
      "region": "South Wales"
    },
    {
      "loc": [
        52.036,
        -4.424037
      ],
      "id": "INCD-18082-e",
      "region": "South Wales"
    },
    {
      "loc": [
        52.7799,
        -2.133488
      ],
      "id": "INCD-31825-m",
      "region": "West Midlands"
    },
    {
      "loc": [
        52.46185,
        -2.082494
      ],
      "id": "INCD-31903-m",
      "region": "West Midlands"
    },
    {
      "loc": [
        52.60434,
        -1.616933
      ],
      "id": "INCD-69451-h",
      "region": "East Midlands"
    },
    {
      "loc": [
        52.89786,
        -1.43299
      ],
      "id": "INCD-69269-h",
      "region": "East Midlands"
    },
    {
      "loc": [
        52.44061,
        -1.477567
      ],
      "id": "INCD-69431-h",
      "region": "East Midlands"
    },
    {
      "loc": [
        52.70811,
        -1.373452
      ],
      "id": "INCD-69450-h",
      "region": "East Midlands"
    }
  ],
  "updatePeriod": 30000,
  "incidentStatus": 200,
  "alertSummary": [
    {
      "displayDate": 1734163200000,
      "id": 8,
      "flagAsNew": true
    }
  ]
}
