{
  "lastUpdated": "2026-01-28T20:49:00.000+0000",
  "twitterEnabled": false,
  "incidents": [
    {
      "loc": [
        51.15876,
        -3.339894
      ],
      "id": "INCD-83914-l",
      "region": "South West"
    },
    {
      "loc": [
        50.483,
        -3.535079
      ],
      "id": "INCD-20544-t",
      "region": "South West"
    },
    {
      "loc": [
        50.13172,
        -5.5529
      ],
      "id": "INCD-83930-l",
      "region": "South West"
    },
    {
      "loc": [
        51.77569,
        -3.21384
      ],
      "id": "INCD-27082-e",
      "region": "South Wales"
    },
    {
      "loc": [
        52.56647,
        -2.147133
      ],
      "id": "INCD-57039-m",
      "region": "West Midlands"
    },
    {
      "loc": [
        52.3967,
        -1.959026
      ],
      "id": "INCD-56984-m",
      "region": "West Midlands"
    },
    {
      "loc": [
        52.0663,
        -2.325099
      ],
      "id": "INCD-57030-m",
      "region": "West Midlands"
    },
    {
      "loc": [
        52.43686,
        -1.893326
      ],
      "id": "INCD-60990-p",
      "region": "West Midlands"
    },
    {
      "loc": [
        52.64523,
        -1.95015
      ],
      "id": "INCD-60967-p",
      "region": "West Midlands"
    },
    {
      "loc": [
        52.74934,
        -2.826819
      ],
      "id": "INCD-57021-m",
      "region": "West Midlands"
    },
    {
      "loc": [
        52.802,
        0.107754
      ],
      "id": "INCD-19348-t",
      "region": "East Midlands"
    },
    {
      "loc": [
        52.49692,
        -0.719177
      ],
      "id": "INCD-115271-h",
      "region": "East Midlands"
    },
    {
      "loc": [
        52.28858,
        -0.86367
      ],
      "id": "INCD-115301-h",
      "region": "East Midlands"
    }
  ],
  "updatePeriod": 30000,
  "incidentStatus": 200,
  "alertSummary": [
    {
      "displayDate": 1759671990139,
      "id": 5,
      "flagAsNew": false
    }
  ]
}
