{
  "lastUpdated": "2024-11-16T05:42:00.000+0000",
  "twitterEnabled": false,
  "incidents": [
    {
      "loc": [
        50.72887,
        -3.05664
      ],
      "id": "INCD-36604-l",
      "region": "South West"
    },
    {
      "loc": [
        51.66056,
        -3.025198
      ],
      "id": "INCD-22416-f",
      "region": "South Wales"
    },
    {
      "loc": [
        52.94759,
        -1.311956
      ],
      "id": "INCD-65409-h",
      "region": "East Midlands"
    },
    {
      "loc": [
        52.62678,
        -1.14677
      ],
      "id": "INCD-65512-h",
      "region": "East Midlands"
    },
    {
      "loc": [
        52.33984,
        -1.573646
      ],
      "id": "INCD-65505-h",
      "region": "East Midlands"
    }
  ],
  "updatePeriod": 30000,
  "incidentStatus": 200,
  "alertSummary": [
    {
      "displayDate": 1724921581191,
      "id": 5,
      "flagAsNew": false
    }
  ]
}
