{
  "lastUpdated": "2024-07-09T09:26:00.000+0100",
  "twitterEnabled": 0,
  "incidents": [
    {
      "loc": [
        50.38806,
        -3.940707
      ],
      "id": "INCD-26120-l",
      "region": "South West"
    },
    {
      "loc": [
        51.44122,
        -2.577632
      ],
      "id": "INCD-26151-l",
      "region": "South West"
    },
    {
      "loc": [
        51.40288,
        -2.603657
      ],
      "id": "INCD-26166-l",
      "region": "South West"
    },
    {
      "loc": [
        51.46375,
        -2.796446
      ],
      "id": "INCD-26167-l",
      "region": "South West"
    },
    {
      "loc": [
        50.67462,
        -3.400728
      ],
      "id": "INCD-26164-l",
      "region": "South West"
    },
    {
      "loc": [
        50.55868,
        -3.486048
      ],
      "id": "INCD-26174-l",
      "region": "South West"
    },
    {
      "loc": [
        50.60053,
        -3.897588
      ],
      "id": "INCD-26189-l",
      "region": "South West"
    },
    {
      "loc": [
        50.87045,
        -4.199019
      ],
      "id": "INCD-26147-l",
      "region": "South West"
    },
    {
      "loc": [
        50.57536,
        -3.478014
      ],
      "id": "INCD-26121-l",
      "region": "South West"
    },
    {
      "loc": [
        50.55612,
        -3.513637
      ],
      "id": "INCD-26152-l",
      "region": "South West"
    },
    {
      "loc": [
        50.70235,
        -3.225984
      ],
      "id": "INCD-26170-l",
      "region": "South West"
    },
    {
      "loc": [
        50.70318,
        -3.228074
      ],
      "id": "INCD-26171-l",
      "region": "South West"
    },
    {
      "loc": [
        50.33458,
        -4.091233
      ],
      "id": "INCD-26162-l",
      "region": "South West"
    },
    {
      "loc": [
        50.43342,
        -3.688479
      ],
      "id": "INCD-26172-l",
      "region": "South West"
    },
    {
      "loc": [
        50.57432,
        -3.474352
      ],
      "id": "INCD-26136-l",
      "region": "South West"
    },
    {
      "loc": [
        50.39783,
        -4.067563
      ],
      "id": "INCD-26161-l",
      "region": "South West"
    },
    {
      "loc": [
        51.19297,
        -2.503585
      ],
      "id": "INCD-26177-l",
      "region": "South West"
    },
    {
      "loc": [
        50.10147,
        -5.275468
      ],
      "id": "INCD-26178-l",
      "region": "South West"
    },
    {
      "loc": [
        51.81285,
        -2.71587
      ],
      "id": "INCD-16249-f",
      "region": "South Wales"
    },
    {
      "loc": [
        52.99943,
        -2.1274
      ],
      "id": "INCD-21612-m",
      "region": "West Midlands"
    },
    {
      "loc": [
        52.05614,
        -1.346208
      ],
      "id": "INCD-25695-p",
      "region": "West Midlands"
    },
    {
      "loc": [
        51.78372,
        -2.610484
      ],
      "id": "INCD-25713-p",
      "region": "West Midlands"
    },
    {
      "loc": [
        53.04296,
        -2.204297
      ],
      "id": "INCD-17069-m",
      "region": "West Midlands"
    },
    {
      "loc": [
        53.04037,
        -2.20779
      ],
      "id": "INCD-21625-m",
      "region": "West Midlands"
    },
    {
      "loc": [
        52.5083,
        -2.159786
      ],
      "id": "INCD-21619-m",
      "region": "West Midlands"
    },
    {
      "loc": [
        52.03622,
        -2.84867
      ],
      "id": "INCD-21613-m",
      "region": "West Midlands"
    },
    {
      "loc": [
        52.13529,
        -2.114206
      ],
      "id": "INCD-25694-p",
      "region": "West Midlands"
    },
    {
      "loc": [
        51.8223,
        -2.51012
      ],
      "id": "INCD-21623-m",
      "region": "West Midlands"
    },
    {
      "loc": [
        52.3169,
        -2.59394
      ],
      "id": "INCD-21622-m",
      "region": "West Midlands"
    },
    {
      "loc": [
        53.1248,
        -2.185095
      ],
      "id": "INCD-25699-p",
      "region": "West Midlands"
    },
    {
      "loc": [
        53.10478,
        -1.34164
      ],
      "id": "INCD-50582-h",
      "region": "East Midlands"
    },
    {
      "loc": [
        53.01195,
        -0.124568
      ],
      "id": "INCD-50586-h",
      "region": "East Midlands"
    },
    {
      "loc": [
        52.9445,
        -1.181583
      ],
      "id": "INCD-50567-h",
      "region": "East Midlands"
    },
    {
      "loc": [
        52.72308,
        -1.144468
      ],
      "id": "INCD-50571-h",
      "region": "East Midlands"
    },
    {
      "loc": [
        52.61573,
        -1.120625
      ],
      "id": "INCD-50578-h",
      "region": "East Midlands"
    }
  ],
  "updatePeriod": 60000,
  "incidentStatus": 200,
  "alertSummary": [
    {
      "id": 6,
      "published": "Mar 15, 2021, 8:00:00 AM",
      "flagAsNew": false,
      "isDefault": true
    }
  ]
}
