{
  "lastUpdated": "2025-08-06T15:26:00.000+0100",
  "twitterEnabled": false,
  "incidents": [
    {
      "loc": [
        50.39771,
        -3.504153
      ],
      "id": "INCD-64847-l",
      "region": "South West"
    },
    {
      "loc": [
        50.71949,
        -3.546265
      ],
      "id": "INCD-64866-l",
      "region": "South West"
    },
    {
      "loc": [
        50.378,
        -4.2105
      ],
      "id": "INCD-64848-l",
      "region": "South West"
    },
    {
      "loc": [
        50.8766,
        -2.789477
      ],
      "id": "INCD-64888-l",
      "region": "South West"
    },
    {
      "loc": [
        50.17195,
        -5.512896
      ],
      "id": "INCD-64767-l",
      "region": "South West"
    },
    {
      "loc": [
        50.39342,
        -3.911309
      ],
      "id": "INCD-64836-l",
      "region": "South West"
    },
    {
      "loc": [
        50.80011,
        -3.19535
      ],
      "id": "INCD-64835-l",
      "region": "South West"
    },
    {
      "loc": [
        50.41967,
        -3.921995
      ],
      "id": "INCD-64837-l",
      "region": "South West"
    },
    {
      "loc": [
        52.24974,
        -2.1947
      ],
      "id": "INCD-14133-l",
      "region": "West Midlands"
    },
    {
      "loc": [
        52.53059,
        -2.006266
      ],
      "id": "INCD-358627-f",
      "region": "West Midlands"
    },
    {
      "loc": [
        53.00017,
        -2.137431
      ],
      "id": "INCD-49515-p",
      "region": "West Midlands"
    },
    {
      "loc": [
        52.4735,
        -1.728895
      ],
      "id": "INCD-49537-p",
      "region": "West Midlands"
    },
    {
      "loc": [
        51.7388,
        -2.273386
      ],
      "id": "INCD-44771-m",
      "region": "West Midlands"
    },
    {
      "loc": [
        52.48396,
        -1.7794
      ],
      "id": "INCD-44457-m",
      "region": "West Midlands"
    },
    {
      "loc": [
        52.98454,
        -2.001195
      ],
      "id": "INCD-358742-f",
      "region": "West Midlands"
    },
    {
      "loc": [
        52.52288,
        -2.002388
      ],
      "id": "INCD-44712-m",
      "region": "West Midlands"
    },
    {
      "loc": [
        52.48093,
        -2.12053
      ],
      "id": "INCD-49522-p",
      "region": "West Midlands"
    },
    {
      "loc": [
        51.9951,
        -1.704309
      ],
      "id": "INCD-14138-l",
      "region": "West Midlands"
    },
    {
      "loc": [
        52.96083,
        -1.21285
      ],
      "id": "INCD-94938-h",
      "region": "East Midlands"
    },
    {
      "loc": [
        52.29662,
        -0.795204
      ],
      "id": "INCD-95026-h",
      "region": "East Midlands"
    },
    {
      "loc": [
        52.38104,
        -1.525254
      ],
      "id": "INCD-95291-h",
      "region": "East Midlands"
    },
    {
      "loc": [
        53.3718,
        -0.882549
      ],
      "id": "INCD-94608-h",
      "region": "East Midlands"
    },
    {
      "loc": [
        52.6479,
        -1.126441
      ],
      "id": "INCD-95238-h",
      "region": "East Midlands"
    },
    {
      "loc": [
        52.38854,
        -0.792615
      ],
      "id": "INCD-95306-h",
      "region": "East Midlands"
    },
    {
      "loc": [
        52.26395,
        -1.533303
      ],
      "id": "INCD-95252-h",
      "region": "East Midlands"
    },
    {
      "loc": [
        52.39085,
        -1.556359
      ],
      "id": "INCD-95262-h",
      "region": "East Midlands"
    }
  ],
  "updatePeriod": 30000,
  "incidentStatus": 200,
  "alertSummary": [
    {
      "displayDate": 1724921581191,
      "id": 5,
      "flagAsNew": false
    }
  ]
}
