{
  "lastUpdated": "2024-12-20T07:30:00.000+0000",
  "twitterEnabled": false,
  "incidents": [
    {
      "loc": [
        51.06314,
        -4.081446
      ],
      "id": "INCD-43175-l",
      "region": "South West"
    },
    {
      "loc": [
        51.83881,
        -3.01386
      ],
      "id": "INCD-24190-f",
      "region": "South Wales"
    },
    {
      "loc": [
        53.07809,
        -2.263054
      ],
      "id": "INCD-355717-f",
      "region": "West Midlands"
    },
    {
      "loc": [
        52.92385,
        -2.381275
      ],
      "id": "INCD-36256-p",
      "region": "West Midlands"
    },
    {
      "loc": [
        51.79559,
        -2.592084
      ],
      "id": "INCD-31942-m",
      "region": "West Midlands"
    },
    {
      "loc": [
        52.67197,
        -2.420989
      ],
      "id": "INCD-32255-m",
      "region": "West Midlands"
    },
    {
      "loc": [
        52.04599,
        -1.3246
      ],
      "id": "INCD-32259-m",
      "region": "West Midlands"
    },
    {
      "loc": [
        52.7781,
        -2.479918
      ],
      "id": "INCD-32229-m",
      "region": "West Midlands"
    },
    {
      "loc": [
        52.93756,
        -1.236529
      ],
      "id": "INCD-70054-h",
      "region": "East Midlands"
    },
    {
      "loc": [
        53.06979,
        -1.374412
      ],
      "id": "INCD-70073-h",
      "region": "East Midlands"
    }
  ],
  "updatePeriod": 30000,
  "incidentStatus": 200,
  "alertSummary": [
    {
      "displayDate": 1734163200000,
      "id": 8,
      "flagAsNew": true
    }
  ]
}
