{
  "lastUpdated": "2026-02-20T09:51:00.000+0000",
  "twitterEnabled": false,
  "incidents": [
    {
      "loc": [
        50.91445,
        -3.22606
      ],
      "id": "INCD-85793-l",
      "region": "South West"
    },
    {
      "loc": [
        51.83881,
        -3.01386
      ],
      "id": "INCD-50084-f",
      "region": "South Wales"
    },
    {
      "loc": [
        53.0542,
        -2.068139
      ],
      "id": "INCD-361075-f",
      "region": "West Midlands"
    },
    {
      "loc": [
        52.3517,
        -2.044514
      ],
      "id": "INCD-62354-p",
      "region": "West Midlands"
    },
    {
      "loc": [
        52.63435,
        -3.006044
      ],
      "id": "INCD-361074-f",
      "region": "West Midlands"
    },
    {
      "loc": [
        53.18846,
        -0.813206
      ],
      "id": "INCD-118011-h",
      "region": "East Midlands"
    }
  ],
  "updatePeriod": 30000,
  "incidentStatus": 200,
  "alertSummary": [
    {
      "displayDate": 1759671990139,
      "id": 5,
      "flagAsNew": false
    }
  ]
}
