{
  "lastUpdated": "2024-05-30T11:41:00.000+0100",
  "twitterEnabled": 0,
  "incidents": [
    {
      "loc": [
        51.53175,
        -2.56282
      ],
      "id": "INCD-23449-l",
      "region": "South West"
    },
    {
      "loc": [
        50.74737,
        -3.546319
      ],
      "id": "INCD-9478-t",
      "region": "South West"
    },
    {
      "loc": [
        50.24742,
        -5.174698
      ],
      "id": "INCD-23453-l",
      "region": "South West"
    },
    {
      "loc": [
        51.16049,
        -3.363612
      ],
      "id": "INCD-23456-l",
      "region": "South West"
    },
    {
      "loc": [
        52.49552,
        -1.828698
      ],
      "id": "INCD-23609-p",
      "region": "West Midlands"
    },
    {
      "loc": [
        52.45255,
        -1.839622
      ],
      "id": "INCD-23611-p",
      "region": "West Midlands"
    },
    {
      "loc": [
        52.33662,
        -3.04207
      ],
      "id": "INCD-19503-m",
      "region": "West Midlands"
    },
    {
      "loc": [
        51.90822,
        -2.063652
      ],
      "id": "INCD-23610-p",
      "region": "West Midlands"
    },
    {
      "loc": [
        53.16922,
        -2.246857
      ],
      "id": "INCD-19505-m",
      "region": "West Midlands"
    },
    {
      "loc": [
        52.03253,
        -2.301181
      ],
      "id": "INCD-23621-p",
      "region": "West Midlands"
    },
    {
      "loc": [
        53.04296,
        -2.204297
      ],
      "id": "INCD-17069-m",
      "region": "West Midlands"
    },
    {
      "loc": [
        52.72331,
        -2.430632
      ],
      "id": "INCD-19520-m",
      "region": "West Midlands"
    },
    {
      "loc": [
        52.48862,
        -1.116211
      ],
      "id": "INCD-46454-h",
      "region": "East Midlands"
    },
    {
      "loc": [
        52.89937,
        -1.861037
      ],
      "id": "INCD-46467-h",
      "region": "East Midlands"
    },
    {
      "loc": [
        53.2217,
        -1.436904
      ],
      "id": "INCD-46424-h",
      "region": "East Midlands"
    },
    {
      "loc": [
        52.8947,
        -0.365039
      ],
      "id": "INCD-46433-h",
      "region": "East Midlands"
    },
    {
      "loc": [
        52.27318,
        -1.598673
      ],
      "id": "INCD-46440-h",
      "region": "East Midlands"
    },
    {
      "loc": [
        52.5738,
        -1.106221
      ],
      "id": "INCD-46464-h",
      "region": "East Midlands"
    },
    {
      "loc": [
        52.94707,
        -1.476892
      ],
      "id": "INCD-46439-h",
      "region": "East Midlands"
    }
  ],
  "updatePeriod": 60000,
  "incidentStatus": 200,
  "alertSummary": [
    {
      "id": 6,
      "published": "Mar 15, 2021, 8:00:00 AM",
      "flagAsNew": false,
      "isDefault": true
    }
  ]
}
