{
  "lastUpdated": "2024-11-04T23:25:00.000+0000",
  "twitterEnabled": false,
  "incidents": [
    {
      "loc": [
        51.58478,
        -2.97768
      ],
      "id": "INCD-21877-f",
      "region": "South Wales"
    },
    {
      "loc": [
        51.71331,
        -3.45365
      ],
      "id": "INCD-21886-f",
      "region": "South Wales"
    },
    {
      "loc": [
        52.22477,
        -2.253234
      ],
      "id": "INCD-32526-p",
      "region": "West Midlands"
    },
    {
      "loc": [
        53.06873,
        -2.14038
      ],
      "id": "INCD-32468-p",
      "region": "West Midlands"
    },
    {
      "loc": [
        53.04243,
        -2.240896
      ],
      "id": "INCD-28453-m",
      "region": "West Midlands"
    },
    {
      "loc": [
        52.53753,
        -1.98378
      ],
      "id": "INCD-32521-p",
      "region": "West Midlands"
    },
    {
      "loc": [
        52.7965,
        -1.612222
      ],
      "id": "INCD-64373-h",
      "region": "East Midlands"
    },
    {
      "loc": [
        52.6096,
        -1.1231
      ],
      "id": "INCD-64270-h",
      "region": "East Midlands"
    },
    {
      "loc": [
        52.25801,
        -1.390477
      ],
      "id": "INCD-64335-h",
      "region": "East Midlands"
    }
  ],
  "updatePeriod": 30000,
  "incidentStatus": 200,
  "alertSummary": [
    {
      "displayDate": 1724921581191,
      "id": 5,
      "flagAsNew": false
    }
  ]
}
