{
  "lastUpdated": "2026-01-21T12:58:00.000+0000",
  "twitterEnabled": false,
  "incidents": [
    {
      "loc": [
        50.35353,
        -4.454633
      ],
      "id": "INCD-41151-v",
      "region": "South West"
    },
    {
      "loc": [
        51.1192,
        -2.988763
      ],
      "id": "INCD-82596-l",
      "region": "South West"
    },
    {
      "loc": [
        50.72632,
        -3.466863
      ],
      "id": "INCD-82591-l",
      "region": "South West"
    },
    {
      "loc": [
        50.81789,
        -3.346537
      ],
      "id": "INCD-82578-l",
      "region": "South West"
    },
    {
      "loc": [
        50.3318,
        -4.790985
      ],
      "id": "INCD-82539-l",
      "region": "South West"
    },
    {
      "loc": [
        50.36896,
        -4.114824
      ],
      "id": "INCD-82586-l",
      "region": "South West"
    },
    {
      "loc": [
        51.51126,
        -2.68803
      ],
      "id": "INCD-82549-l",
      "region": "South West"
    },
    {
      "loc": [
        51.69772,
        -3.893193
      ],
      "id": "INCD-26860-e",
      "region": "South Wales"
    },
    {
      "loc": [
        52.648,
        -2.889491
      ],
      "id": "INCD-56398-m",
      "region": "West Midlands"
    },
    {
      "loc": [
        52.38979,
        -2.00911
      ],
      "id": "INCD-56433-m",
      "region": "West Midlands"
    },
    {
      "loc": [
        52.41449,
        -1.77992
      ],
      "id": "INCD-60353-p",
      "region": "West Midlands"
    },
    {
      "loc": [
        52.44094,
        -2.831654
      ],
      "id": "INCD-56390-m",
      "region": "West Midlands"
    },
    {
      "loc": [
        52.7315,
        -1.891883
      ],
      "id": "INCD-56412-m",
      "region": "West Midlands"
    },
    {
      "loc": [
        52.58117,
        -2.1138
      ],
      "id": "INCD-55936-m",
      "region": "West Midlands"
    },
    {
      "loc": [
        51.92174,
        -2.589816
      ],
      "id": "INCD-56431-m",
      "region": "West Midlands"
    },
    {
      "loc": [
        52.62151,
        -1.63733
      ],
      "id": "INCD-112435-h",
      "region": "East Midlands"
    },
    {
      "loc": [
        52.72857,
        -1.34267
      ],
      "id": "INCD-114332-h",
      "region": "East Midlands"
    },
    {
      "loc": [
        52.363,
        -1.284733
      ],
      "id": "INCD-114195-h",
      "region": "East Midlands"
    },
    {
      "loc": [
        52.96155,
        -0.013619
      ],
      "id": "INCD-113950-h",
      "region": "East Midlands"
    },
    {
      "loc": [
        53.09079,
        0.005485
      ],
      "id": "INCD-114288-h",
      "region": "East Midlands"
    }
  ],
  "updatePeriod": 30000,
  "incidentStatus": 200,
  "alertSummary": [
    {
      "displayDate": 1768912200000,
      "id": 6,
      "flagAsNew": true
    }
  ]
}
