{
  "lastUpdated": "2025-07-20T00:42:00.000+0100",
  "twitterEnabled": false,
  "incidents": [
    {
      "loc": [
        50.35832,
        -3.645533
      ],
      "id": "INCD-63202-l",
      "region": "South West"
    },
    {
      "loc": [
        51.04116,
        -2.930987
      ],
      "id": "INCD-63207-l",
      "region": "South West"
    },
    {
      "loc": [
        50.35134,
        -4.216337
      ],
      "id": "INCD-63199-l",
      "region": "South West"
    },
    {
      "loc": [
        50.34644,
        -4.482141
      ],
      "id": "INCD-63204-l",
      "region": "South West"
    },
    {
      "loc": [
        50.8809,
        -3.926545
      ],
      "id": "INCD-63209-l",
      "region": "South West"
    },
    {
      "loc": [
        51.40186,
        -2.347805
      ],
      "id": "INCD-63193-l",
      "region": "South West"
    },
    {
      "loc": [
        50.79181,
        -3.652525
      ],
      "id": "INCD-63211-l",
      "region": "South West"
    },
    {
      "loc": [
        52.51008,
        -2.112113
      ],
      "id": "INCD-358556-f",
      "region": "West Midlands"
    },
    {
      "loc": [
        51.88309,
        -2.061568
      ],
      "id": "INCD-48488-p",
      "region": "West Midlands"
    },
    {
      "loc": [
        52.2261,
        -2.255701
      ],
      "id": "INCD-43753-m",
      "region": "West Midlands"
    },
    {
      "loc": [
        52.28205,
        -2.84446
      ],
      "id": "INCD-48494-p",
      "region": "West Midlands"
    },
    {
      "loc": [
        52.55773,
        -1.798956
      ],
      "id": "INCD-43733-m",
      "region": "West Midlands"
    },
    {
      "loc": [
        52.27923,
        -2.841962
      ],
      "id": "INCD-43754-m",
      "region": "West Midlands"
    },
    {
      "loc": [
        53.23103,
        -0.540293
      ],
      "id": "INCD-93451-h",
      "region": "East Midlands"
    },
    {
      "loc": [
        52.87327,
        -0.163216
      ],
      "id": "INCD-93463-h",
      "region": "East Midlands"
    },
    {
      "loc": [
        52.24186,
        -0.872216
      ],
      "id": "INCD-93454-h",
      "region": "East Midlands"
    },
    {
      "loc": [
        52.80177,
        -0.38566
      ],
      "id": "INCD-93447-h",
      "region": "East Midlands"
    },
    {
      "loc": [
        52.3148,
        -0.687237
      ],
      "id": "INCD-93452-h",
      "region": "East Midlands"
    }
  ],
  "updatePeriod": 30000,
  "incidentStatus": 200,
  "alertSummary": [
    {
      "displayDate": 1724921581191,
      "id": 5,
      "flagAsNew": false
    }
  ]
}
